pydantic/__init__.py
pydantic/_hypothesis_plugin.py
pydantic/annotated_types.py
pydantic/class_validators.py
pydantic/color.py
pydantic/config.py
pydantic/dataclasses.py
pydantic/datetime_parse.py
pydantic/decorator.py
pydantic/env_settings.py
pydantic/error_wrappers.py
pydantic/errors.py
pydantic/fields.py
pydantic/generics.py
pydantic/json.py
pydantic/main.py
pydantic/mypy.py
pydantic/networks.py
pydantic/parse.py
pydantic/py.typed
pydantic/schema.py
pydantic/tools.py
pydantic/types.py
pydantic/typing.py
pydantic/utils.py
pydantic/validators.py
pydantic/version.py
pydantic1-1.10.13.dist-info/LICENSE
pydantic1-1.10.13.dist-info/METADATA
pydantic1-1.10.13.dist-info/WHEEL
pydantic1-1.10.13.dist-info/entry_points.txt
pydantic1-1.10.13.dist-info/top_level.txt
pydantic1-1.10.13.dist-info/RECORD
