Metadata-Version: 2.1
Name: pydantic1
Version: 1.10.13
Summary: Data validation and settings management using python type hints
Home-page: https://github.com/pydantic/pydantic
Author: Samuel Colvin
Author-email: s@muelcolvin.com
License: MIT
Classifier: Development Status :: 5 - Production/Stable
Classifier: Programming Language :: Python
Classifier: Programming Language :: Python :: 3
Classifier: Programming Language :: Python :: 3 :: Only
Classifier: Programming Language :: Python :: 3.7
Classifier: Programming Language :: Python :: 3.8
Classifier: Programming Language :: Python :: 3.9
Classifier: Programming Language :: Python :: 3.10
Classifier: Programming Language :: Python :: 3.11
Classifier: Intended Audience :: Developers
Classifier: Intended Audience :: Information Technology
Classifier: Intended Audience :: System Administrators
Classifier: License :: OSI Approved :: MIT License
Classifier: Operating System :: Unix
Classifier: Operating System :: POSIX :: Linux
Classifier: Environment :: Console
Classifier: Environment :: MacOS X
Classifier: Framework :: Hypothesis
Classifier: Framework :: Pydantic
Classifier: Topic :: Software Development :: Libraries :: Python Modules
Classifier: Topic :: Internet
Requires-Python: >=3.7
License-File: LICENSE
Requires-Dist: typing-extensions>=4.2.0
Provides-Extra: email
Requires-Dist: email-validator>=1.0.3; extra == "email"
Provides-Extra: dotenv
Requires-Dist: python-dotenv>=0.10.4; extra == "dotenv"
